{
  "id": "cross-compile",
  "title": "Cross Compile",
  "phase": 4,
  "phaseName": "System Programming & IPC",
  "category": "Phase 4 - System Programming & IPC",
  "subcategory": "system-programming",
  "language": "cpp",
  "description": "x86-64 microarchitecture levels (x86-64-v1 through v4) define. -march=native is dangerous across machines: a binary built on",
  "content": "<h2 id=\"section-key-learning-points\">Key Learning Points</h2>\n<ul>\n<li>x86-64 microarchitecture levels (x86-64-v1 through v4) define</li>\n<li>-march=native is dangerous across machines: a binary built on</li>\n<li>CPU feature detection at runtime uses cpuid (x86) or getauxval</li>\n<li>Function multi-versioning (GCC IFUNC / clang multiversion)</li>\n<li>For cross-compilation: use a sysroot (e.g., via crosstool-NG</li>\n</ul>\n<h2 id=\"section-usage\">Usage</h2>\n<p>// g++ -O3 -std=c++20 -march=x86-64-v2 ZHFT_CROSS_COMPILE.txt -o dispatch\n// ./dispatch</p>\n<h2 id=\"section-source-code\">Source Code</h2>\n<pre><code class=\"language-cpp\">#include &lt;array&gt;\n#include &lt;bit&gt;\n#include &lt;cstdint&gt;\n#include &lt;cstdio&gt;\n#include &lt;cstring&gt;\n#include &lt;iostream&gt;\n#include &lt;string_view&gt;\n\n#if defined(__linux__) &amp;&amp; defined(__x86_64__)\n#include &lt;cpuid.h&gt;\n#include &lt;elf.h&gt;\n#include &lt;sys/auxv.h&gt;\n#endif\n\n// -------------------------------------------------------------------\n// x86-64 CPU feature set (subset relevant to HFT).\n// -------------------------------------------------------------------\nstruct CpuFeatures {\n    bool sse4_2    : 1;\n    bool popcnt    : 1;\n    bool avx       : 1;\n    bool avx2      : 1;\n    bool bmi1      : 1;\n    bool bmi2      : 1;\n    bool avx512f   : 1;\n    bool avx512bw  : 1;\n    bool avx512dq  : 1;\n    bool avx512vl  : 1;\n    bool clflushopt: 1;\n    bool rdtscp    : 1;\n    bool invariant_tsc : 1;\n    bool xsave     : 1;\n    bool xsavec    : 1;\n    bool xgetbv    : 1;\n\n    // Human-readable summary.\n    auto ToString() const -&gt; std::string {\n        std::string s;\n        auto add = [&amp;](const char* name, bool val) {\n            if (val) { if (!s.empty()) s += &quot;, &quot;; s += name; }\n        };\n        add(&quot;SSE4.2&quot;, sse4_2); add(&quot;POPCNT&quot;, popcnt);\n        add(&quot;AVX&quot;, avx); add(&quot;AVX2&quot;, avx2);\n        add(&quot;BMI1&quot;, bmi1); add(&quot;BMI2&quot;, bmi2);\n        add(&quot;AVX512F&quot;, avx512f); add(&quot;AVX512BW&quot;, avx512bw);\n        add(&quot;AVX512DQ&quot;, avx512dq); add(&quot;AVX512VL&quot;, avx512vl);\n        add(&quot;CLFLUSHOPT&quot;, clflushopt); add(&quot;RDTSCP&quot;, rdtscp);\n        add(&quot;INVARIANT_TSC&quot;, invariant_tsc);\n        return s;\n    }\n\n    // Determine microarchitecture level.\n    auto MicroarchLevel() const -&gt; int {\n        if (avx512f)  return 4;    // v4 = AVX512F + AVX512BW/DQ/VL\n        if (avx2)     return 3;    // v3 = AVX + AVX2 + BMI\n        if (sse4_2)   return 2;    // v2 = SSE4.2 + POPCNT\n        return 1;                   // v1 = baseline x86-64\n    }\n};\n\n// -------------------------------------------------------------------\n// Singleton CPU feature detector — call once, cache forever.\n// -------------------------------------------------------------------\nclass CpuInfo {\npublic:\n    static auto Instance() -&gt; const CpuInfo&amp; {\n        static CpuInfo instance;\n        return instance;\n    }\n\n    auto Features() const -&gt; const CpuFeatures&amp; { return features_; }\n    auto Level() const -&gt; int { return features_.MicroarchLevel(); }\n\nprivate:\n    CpuInfo() { Detect(); }\n\n    void Detect() {\n#if defined(__x86_64__)\n        uint32_t eax, ebx, ecx, edx;\n\n        // Maximum standard leaf.\n        if (__get_cpuid(0, &amp;eax, &amp;ebx, &amp;ecx, &amp;edx) == 0) return;\n\n        // Leaf 1: feature bits.\n        if (__get_cpuid(1, &amp;eax, &amp;ebx, &amp;ecx, &amp;edx) != 0) {\n            features_.sse4_2 = (ecx &gt;&gt; 20) &amp; 1;\n            features_.popcnt = (ecx &gt;&gt; 23) &amp; 1;\n            features_.xsave  = (ecx &gt;&gt; 26) &amp; 1;\n            features_.rdtscp = (ecx &gt;&gt; 27) &amp; 1;\n            features_.xgetbv = ((ecx &gt;&gt; 26) &amp; 1) &amp;&amp; ((ecx &gt;&gt; 27) &amp; 1);\n        }\n\n        // Leaf 7 (subleaf 0): extended features (AVX2, BMI, AVX512).\n        if (__get_cpuid_count(7, 0, &amp;eax, &amp;ebx, &amp;ecx, &amp;edx) != 0) {\n            features_.bmi1    = (ebx &gt;&gt; 3) &amp; 1;\n            features_.avx2    = (ebx &gt;&gt; 5) &amp; 1;\n            features_.bmi2    = (ebx &gt;&gt; 8) &amp; 1;\n            features_.avx512f = (ebx &gt;&gt; 16) &amp; 1;\n            features_.avx512dq = (ebx &gt;&gt; 17) &amp; 1;\n            features_.avx512bw = (ebx &gt;&gt; 30) &amp; 1;\n            features_.avx512vl = (ebx &gt;&gt; 31) &amp; 1;\n            features_.avx     = features_.avx2;   // AVX implied by AVX2\n            features_.clflushopt = (ebx &gt;&gt; 23) &amp; 1;\n        }\n\n        // Check OS XSAVE support (AVX require OS context save).\n        if (features_.xgetbv) {\n            uint64_t xcr0;\n            asm volatile(&quot;xgetbv&quot; : &quot;=a&quot;(eax), &quot;=d&quot;(edx) : &quot;c&quot;(0));\n            xcr0 = (static_cast&lt;uint64_t&gt;(edx) &lt;&lt; 32) | eax;\n            features_.avx  = features_.avx  &amp;&amp; ((xcr0 &gt;&gt; 1) &amp; 1);   // YMM\n            features_.avx2 = features_.avx2 &amp;&amp; ((xcr0 &gt;&gt; 1) &amp; 1);\n            features_.avx512f = features_.avx512f &amp;&amp; ((xcr0 &gt;&gt; 5) &amp; 1); // OPMASK/ZMM\n        }\n\n        // Check invariant TSC via /proc/cpuinfo or auxv.\n        // On Linux, getauxval(AT_HWCAP) includes this on modern kernels.\n#if defined(__linux__)\n        unsigned long hwcaps = getauxval(AT_HWCAP);\n        (void)hwcaps;\n#endif\n        // The invariant TSC flag is usually in leaf 0x80000007.\n        if (__get_cpuid(0x80000007, &amp;eax, &amp;ebx, &amp;ecx, &amp;edx) != 0) {\n            features_.invariant_tsc = (edx &gt;&gt; 8) &amp; 1;\n        }\n#endif\n    }\n\n    CpuFeatures features_ = {};\n};\n\n// -------------------------------------------------------------------\n// SIMD routine dispatch layer using IFUNC (GCC).\n// This lets the linker pick the best implementation at load time.\n// -------------------------------------------------------------------\n\n// Scalar fallback: sum array of int64 (simple example).\nauto SumScalar(const int64_t* data, std::size_t n) -&gt; int64_t {\n    int64_t sum = 0;\n    for (std::size_t i = 0; i &lt; n; ++i) sum += data[i];\n    return sum;\n}\n\n// AVX2 vectorised sum.\n#if defined(__AVX2__)\n#include &lt;immintrin.h&gt;\nauto SumAVX2(const int64_t* data, std::size_t n) -&gt; int64_t {\n    __m256i sum_vec = _mm256_setzero_si256();\n    std::size_t i = 0;\n    for (; i + 4 &lt;= n; i += 4) {\n        __m256i v = _mm256_loadu_si256(reinterpret_cast&lt;const __m256i*&gt;(data + i));\n        sum_vec = _mm256_add_epi64(sum_vec, v);\n    }\n    int64_t sum = 0;\n    alignas(32) int64_t tmp[4];\n    _mm256_store_si256(reinterpret_cast&lt;__m256i*&gt;(tmp), sum_vec);\n    for (int j = 0; j &lt; 4; ++j) sum += tmp[j];\n    for (; i &lt; n; ++i) sum += data[i];\n    return sum;\n}\n#endif\n\n// -------------------------------------------------------------------\n// IFUNC resolver: called once at program load time.\n// Returns pointer to the best implementation for this CPU.\n// -------------------------------------------------------------------\n#if defined(__GNUC__) &amp;&amp; !defined(__clang__) &amp;&amp; defined(__AVX2__)\nstatic auto ResolveSum() -&gt; decltype(&amp;SumScalar) {\n    const auto&amp; f = CpuInfo::Instance().Features();\n    if (f.avx2) return SumAVX2;\n    return SumScalar;\n}\n\n// The IFUNC attribute tells the linker to call ResolveSum() at load time.\nauto SumDispatch(const int64_t* data, std::size_t n) -&gt; int64_t\n    __attribute__((ifunc(&quot;ResolveSum&quot;)));\n#else\n// Clang or non-IFUNC: just use scalar (or manual dispatch).\nauto SumDispatch(const int64_t* data, std::size_t n) -&gt; int64_t {\n    const auto&amp; f = CpuInfo::Instance().Features();\n#if defined(__AVX2__)\n    if (f.avx2) return SumAVX2(data, n);\n#endif\n    return SumScalar(data, n);\n}\n#endif\n\n// -------------------------------------------------------------------\n// Manual runtime dispatch (alternative to IFUNC) — for compilers\n// that don't support IFUNC. Slightly higher overhead (indirect call\n// via function pointer loaded from cache).\n// -------------------------------------------------------------------\nusing SumFn = auto (*)(const int64_t*, std::size_t) -&gt; int64_t;\n\nauto GetSumImpl() -&gt; SumFn {\n    const auto&amp; f = CpuInfo::Instance().Features();\n    if (f.avx2) {\n#if defined(__AVX2__)\n        return SumAVX2;\n#endif\n    }\n    return SumScalar;\n}\n\n// -------------------------------------------------------------------\n// Demonstration.\n// -------------------------------------------------------------------\nauto main() -&gt; int {\n    const auto&amp; info  = CpuInfo::Instance();\n    const auto&amp; feats = info.Features();\n\n    std::cout &lt;&lt; &quot;=== CPU Feature Detection ===\\n&quot;;\n    std::cout &lt;&lt; &quot;Microarchitecture level: x86-64-v&quot; &lt;&lt; info.Level() &lt;&lt; &quot;\\n&quot;;\n    std::cout &lt;&lt; &quot;Features: &quot; &lt;&lt; feats.ToString() &lt;&lt; &quot;\\n\\n&quot;;\n\n    // Benchmark IFUNC dispatch.\n    std::array&lt;int64_t, 1024&gt; data{};\n    for (auto&amp; v : data) v = 1;\n\n    volatile auto result = SumDispatch(data.data(), data.size());\n\n    auto sum_fn = GetSumImpl();\n    volatile auto result2 = sum_fn(data.data(), data.size());\n\n    std::cout &lt;&lt; &quot;Sum (IFUNC dispatch): &quot; &lt;&lt; result &lt;&lt; &quot;\\n&quot;;\n    std::cout &lt;&lt; &quot;Sum (manual dispatch): &quot; &lt;&lt; result2 &lt;&lt; &quot;\\n\\n&quot;;\n\n    std::cout &lt;&lt; &quot;=== Recommendations ===\\n&quot;;\n    std::cout &lt;&lt; &quot;1. For cross-compilation: use -march=x86-64-v3 (not -march=native)\\n&quot;;\n    std::cout &lt;&lt; &quot;2. Use IFUNC for hot-path numeric routines\\n&quot;;\n    std::cout &lt;&lt; &quot;3. Cache CpuInfo::Instance() once at startup\\n&quot;;\n    std::cout &lt;&lt; &quot;4. For deploy: build fat binary with multiple -march variants\\n&quot;;\n    std::cout &lt;&lt; &quot;   and use dlopen() to load the best at runtime\\n&quot;;\n\n    return 0;\n}</code></pre>",
  "sections": [
    {
      "id": "key-learning-points",
      "title": "Key Learning Points"
    },
    {
      "id": "usage",
      "title": "Usage"
    },
    {
      "id": "source-code",
      "title": "Source Code"
    }
  ],
  "tags": [
    "phase-4"
  ],
  "type": "reference",
  "toc": false
}