{
  "id": "top-of-book",
  "title": "Top Of Book",
  "phase": 9,
  "phaseName": "Order Book & Microstructure",
  "category": "Phase 9 - Order Book & Microstructure",
  "subcategory": "order-book",
  "language": "cpp",
  "description": "Bandwidth/latency tradeoff: Top-of-book (ToB) = 2 price+size. Full book parsing cost: processing 100 levels takes ~1-2 us",
  "content": "<h2 id=\"section-key-learning-points\">Key Learning Points</h2>\n<ul>\n<li>Bandwidth/latency tradeoff: Top-of-book (ToB) = 2 price+size</li>\n<li>Full book parsing cost: processing 100 levels takes ~1-2 us</li>\n<li>Information content: full book provides order flow pressure,</li>\n<li>Quote stuffing identification: rapid order add/cancel on same</li>\n<li>Book depth relevance by strategy:</li>\n</ul>\n<h2 id=\"section-usage\">Usage</h2>\n<pre><code class=\"language-bash\">\nStrategyBookFit fit;\nfit.evaluate(StrategyType::MARKET_MAKING);\nauto result = fit.recommend(); // &quot;full-book&quot;</code></pre>\n<h2 id=\"section-source-code\">Source Code</h2>\n<pre><code class=\"language-cpp\">#include &lt;algorithm&gt;\n#include &lt;array&gt;\n#include &lt;bit&gt;\n#include &lt;cmath&gt;\n#include &lt;cstdint&gt;\n#include &lt;cstring&gt;\n#include &lt;string_view&gt;\n#include &lt;vector&gt;\n\n// ---------------------------------------------------------------------------\n// Bandwidth calculator\n// ---------------------------------------------------------------------------\nclass BandwidthCalculator {\npublic:\n  struct BandwidthEstimate {\n    double mbps;        // Megabits per second\n    uint64_t msgs_per_sec;\n    double parse_time_us; // Per message\n  };\n\n  // Estimate bandwidth for ToB vs full book\n  // Assumes: 100,000 updates/sec (active futures contract at peak)\n  static BandwidthEstimate estimate(bool full_book, uint64_t updates_per_sec = 100000) {\n    // ToB: ~50 bytes (bid px, bid sz, ask px, ask sz, seq)\n    // Full: ~500 bytes (10 levels × 2 sides × 25 bytes)\n    size_t msg_size = full_book ? 500 : 50;\n    double mbps = (msg_size * 8.0 * updates_per_sec) / 1'000'000.0;\n    double parse_us = full_book ? 1.5 : 0.1; // microseconds\n\n    return {mbps, updates_per_sec, parse_us};\n  }\n\n  // Savings from ToB vs full book\n  struct Savings {\n    double bandwidth_pct;\n    double parse_time_pct;\n    double info_loss; // subjective\n  };\n\n  static Savings computeSavings() {\n    auto full = estimate(true);\n    auto tob  = estimate(false);\n    return {\n      (full.mbps - tob.mbps) / full.mbps * 100.0,\n      (full.parse_time_us - tob.parse_time_us) / full.parse_time_us * 100.0,\n      0.35 // ~35% information loss (heuristic)\n    };\n  }\n};\n\n// ---------------------------------------------------------------------------\n// Book depth analyzer\n// ---------------------------------------------------------------------------\nclass BookDepthAnalyzer {\npublic:\n  struct DepthSignal {\n    double toB_bid_ask_gap;\n    uint64_t total_bid_depth_10levels;\n    uint64_t total_ask_depth_10levels;\n    double imbalance_10levels;\n    bool   has_iceberg_cluster;\n    uint64_t cancel_to_order_ratio; // quote stuffing indicator\n  };\n\n  DepthSignal analyze(bool use_full_book) {\n    if (!use_full_book) {\n      // ToB only: can only compute basic bid/ask\n      return {/* bid_ask_gap */ 0.25, 0, 0, 0, false, 0};\n    }\n    // Full book: comprehensive analysis\n    return {/* bid_ask_gap */ 0.25, 50000, 48000, 0.02, true, 3};\n  }\n};\n\n// ---------------------------------------------------------------------------\n// Strategy-book fit matrix\n// ---------------------------------------------------------------------------\n/* MATRIX: Strategy vs Book Depth Fit\n *\n * +-------------------+------------+--------------+-------------------+\n * | Strategy          | Book Depth | Why?         | Info Value        |\n * +-------------------+------------+--------------+-------------------+\n * | Market Making     | Full       | Walls,       | Critical          |\n * |                   | (10+ lvl)  | icebergs,    | (positioning)     |\n * |                   |            | imbalance    |                   |\n * | Arbitrage         | ToB        | Price diff   | Sufficient        |\n * | (lat arb, ETF)    |            | only needed  |                   |\n * | Momentum          | Full       | Order flow,  | Important         |\n * |                   | (5-10 lvl) | accumulation |                   |\n * | Mean Reversion    | ToB        | Signal from  | Usually enough    |\n * |                   |            | bid/ask only |                   |\n * | Statistical Arb   | ToB        | Cross-       | Sufficient        |\n * |                   |            | sectional   |                   |\n * | Iceberg Detection | Full       | Inherently   | Requires          |\n * |                   | (all)      | needs depth  | full depth        |\n * | Quote Stuffing    | Full       | Pattern      | Requires          |\n * | Detection         | (all)      | at same level| full depth        |\n * | VPIN / Flow Tox   | Full       | Volume at    | Better with       |\n * |                   | (5+ lvl)   | each level   | full depth        |\n * +-------------------+------------+--------------+-------------------+\n *\n * Recommendation:\n *   - If &lt;= 1 Gbps bandwidth: use ToB + occasional depth snapshot\n *   - If &gt;= 10 Gbps: use full book (10 levels) always\n *   - Hybrid: subscribe to ToB incremental + full book snapshot every 1ms\n */\n\nenum class StrategyType : uint8_t {\n  MARKET_MAKING,\n  ARBITRAGE,\n  MOMENTUM,\n  MEAN_REVERSION,\n  STAT_ARB,\n};\n\nclass StrategyBookFit {\npublic:\n  struct Recommendation {\n    bool   use_full_book;\n    uint8_t depth_levels;\n    std::string_view reason;\n  };\n\n  Recommendation recommend(StrategyType type) const {\n    switch (type) {\n    case StrategyType::MARKET_MAKING:\n      return {true, 10, &quot;Need walls, icebergs, imbalance&quot;};\n    case StrategyType::ARBITRAGE:\n      return {false, 1, &quot;Price diff only needs ToB&quot;};\n    case StrategyType::MOMENTUM:\n      return {true, 5, &quot;Order flow requires some depth&quot;};\n    case StrategyType::MEAN_REVERSION:\n      return {false, 1, &quot;ToB usually sufficient&quot;};\n    case StrategyType::STAT_ARB:\n      return {false, 1, &quot;Cross-sectional, ToB enough&quot;};\n    default:\n      return {false, 1, &quot;Default to ToB&quot;};\n    }\n  }\n};</code></pre>\n<h2 id=\"section-decision-matrix\">Decision Matrix</h2>\n<p>| : Strategy vs Book Depth Fit |\n| --- |\n| +-------------------+------------+--------------+-------------------+ |\n| Strategy | Book Depth | Why? | Info Value |\n| +-------------------+------------+--------------+-------------------+ |\n| Market Making | Full | Walls, | Critical |\n| (10+ lvl) | icebergs, | (positioning) |\n| imbalance |\n| Arbitrage | ToB | Price diff | Sufficient |\n| (lat arb, ETF) | only needed |\n| Momentum | Full | Order flow, | Important |\n| (5-10 lvl) | accumulation |\n| Mean Reversion | ToB | Signal from | Usually enough |\n| bid/ask only |\n| Statistical Arb | ToB | Cross- | Sufficient |\n| sectional |\n| Iceberg Detection | Full | Inherently | Requires |\n| (all) | needs depth | full depth |\n| Quote Stuffing | Full | Pattern | Requires |\n| Detection | (all) | at same level | full depth |\n| VPIN / Flow Tox | Full | Volume at | Better with |\n| (5+ lvl) | each level | full depth |\n| +-------------------+------------+--------------+-------------------+ |\n| Recommendation: |\n| - If <= 1 Gbps bandwidth: use ToB + occasional depth snapshot |\n| - If >= 10 Gbps: use full book (10 levels) always |\n| - Hybrid: subscribe to ToB incremental + full book snapshot every 1ms |</p>",
  "sections": [
    {
      "id": "key-learning-points",
      "title": "Key Learning Points"
    },
    {
      "id": "usage",
      "title": "Usage"
    },
    {
      "id": "source-code",
      "title": "Source Code"
    },
    {
      "id": "decision-matrix",
      "title": "Decision Matrix"
    }
  ],
  "tags": [
    "phase-9"
  ],
  "type": "decision-matrix",
  "toc": false
}